{
    "AX": {
        "error": 0.008835209476304322,
        "error_type": "SEM",
        "filter_outliers_dict": {
            "filter_outliers": true,
            "iterations": 1,
            "std_devs": 3,
            "use_iqr_filtering": false,
            "use_standard_deviation_filtering": false
        },
        "fit": "Average",
        "fn": 45,
        "include_baseline_error": true,
        "n": 45,
        "outlier_excluded": [],
        "reviewed": true,
        "user_excluded": [],
        "value": -0.20653142382701237
    },
    "CDD": {
        "error": 2.3682051626065562e-05,
        "error_type": "SEM",
        "filter_outliers_dict": {
            "filter_outliers": true,
            "iterations": 1,
            "std_devs": 10,
            "use_iqr_filtering": false,
            "use_standard_deviation_filtering": false
        },
        "fit": "Average",
        "fn": 45,
        "include_baseline_error": true,
        "n": 45,
        "outlier_excluded": [],
        "reviewed": true,
        "user_excluded": [],
        "value": 0.00013909679546486586
    },
    "H1": {
        "error": 0.006643608342129142,
        "error_type": "SEM",
        "filter_outliers_dict": {
            "filter_outliers": true,
            "iterations": 1,
            "std_devs": 3,
            "use_iqr_filtering": false,
            "use_standard_deviation_filtering": false
        },
        "fit": "Average",
        "fn": 45,
        "include_baseline_error": true,
        "n": 45,
        "outlier_excluded": [],
        "reviewed": true,
        "user_excluded": [],
        "value": 0.036963886940308534
    },
    "H2": {
        "error": 0.002957890532532118,
        "error_type": "SEM",
        "filter_outliers_dict": {
            "filter_outliers": true,
            "iterations": 1,
            "std_devs": 2
        },
        "fit": "average",
        "value": -0.017541542218349197
    },
    "L1": {
        "error": 0.004354033195057287,
        "error_type": "SEM",
        "filter_outliers_dict": {
            "filter_outliers": true,
            "iterations": 1,
            "std_devs": 3,
            "use_iqr_filtering": false,
            "use_standard_deviation_filtering": false
        },
        "fit": "Average",
        "fn": 45,
        "include_baseline_error": true,
        "n": 45,
        "outlier_excluded": [],
        "reviewed": true,
        "user_excluded": [],
        "value": 0.016530717505762973
    },
    "L2": {
        "error": 0.007107659176749412,
        "error_type": "SEM",
        "filter_outliers_dict": {
            "filter_outliers": true,
            "iterations": 1,
            "std_devs": 3,
            "use_iqr_filtering": false,
            "use_standard_deviation_filtering": false
        },
        "fit": "Average",
        "fn": 45,
        "include_baseline_error": true,
        "n": 45,
        "outlier_excluded": [],
        "reviewed": true,
        "user_excluded": [],
        "value": -0.06358232694005386
    }
}